VERILOG/verilog.v
`timescale 1ns/1ps

module verilog(sum, c4, A, B, clk, reset);

    input [3:0] A, B;
    input clk, reset;
    output [3:0] sum;
    output c4;

    wire [3:0] A_ff, B_ff, sum_int;
    wire c4_int;
    wire C0 = 0;

    dff dff_a0(.d(A[0]), .clk(clk), .reset(reset), .q(A_ff[0]));
    dff dff_a1(.d(A[1]), .clk(clk), .reset(reset), .q(A_ff[1]));
    dff dff_a2(.d(A[2]), .clk(clk), .reset(reset), .q(A_ff[2]));
    dff dff_a3(.d(A[3]), .clk(clk), .reset(reset), .q(A_ff[3]));

    dff dff_b0(.d(B[0]), .clk(clk), .reset(reset), .q(B_ff[0]));
    dff dff_b1(.d(B[1]), .clk(clk), .reset(reset), .q(B_ff[1]));
    dff dff_b2(.d(B[2]), .clk(clk), .reset(reset), .q(B_ff[2]));
    dff dff_b3(.d(B[3]), .clk(clk), .reset(reset), .q(B_ff[3]));

    adder_4bit_cla cla_inst(
        .sum(sum_int), 
        .c4(c4_int), 
        .A(A_ff), 
        .B(B_ff), 
        .C0(C0)
    );

    dff dff_s0(.d(sum_int[0]), .clk(clk), .reset(reset), .q(sum[0]));
    dff dff_s1(.d(sum_int[1]), .clk(clk), .reset(reset), .q(sum[1]));
    dff dff_s2(.d(sum_int[2]), .clk(clk), .reset(reset), .q(sum[2]));
    dff dff_s3(.d(sum_int[3]), .clk(clk), .reset(reset), .q(sum[3]));

    dff dff_c4(.d(c4_int), .clk(clk), .reset(reset), .q(c4));

endmodule

module dff(d, clk, reset, q);
    input d, clk, reset;
    output reg q;

    always @(posedge clk or posedge reset) begin
        if (reset)
            q <= 0;
        else
            q <= d;
    end
endmodule

module adder_4bit_cla(sum, c4, A, B, C0);

    input [3:0] A, B;
    input C0;
    output [3:0] sum;
    output c4;

    wire P0, G0, P1, G1, P2, G2, P3, G3;
    wire C4, C3, C2, C1;

    assign
        P0 = A[0] ^ B[0],
        P1 = A[1] ^ B[1],
        P2 = A[2] ^ B[2],
        P3 = A[3] ^ B[3];

    assign
        G0 = A[0] & B[0],
        G1 = A[1] & B[1],
        G2 = A[2] & B[2],
        G3 = A[3] & B[3];

    assign
        C1 = G0 | (P0 & C0),
        C2 = G1 | (P1 & G0) | (P1 & P0 & C0),
        C3 = G2 | (P2 & G1) | (P2 & P1 & G0) | (P2 & P1 & P0 & C0),
        C4 = G3 | (P3 & G2) | (P3 & P2 & G1) | (P3 & P2 & P1 & G0) | (P3 & P2 & P1 & P0 & C0);

    assign
        sum[0] = P0 ^ C0,
        sum[1] = P1 ^ C1,
        sum[2] = P2 ^ C2,
        sum[3] = P3 ^ C3;

    assign c4 = C4;

endmodule

VERILOG/testbench.v

module testbench;

    reg [3:0] A, B;
    reg clk, reset;
    wire [3:0] sum;
    wire c4;

    verilog uut (
        .A(A),
        .B(B),
        .clk(clk),
        .reset(reset),
        .sum(sum),
        .c4(c4)
    );

    initial begin
        $dumpfile("test.vcd");
        $dumpvars(0,testbench);
        A = 4'b0000;
        B = 4'b0000;
        reset = 1;
        clk = 0;
        #10 reset = 0;
        #20 A[0] = 1'b1; B[0] = 1'b1;
        #40 A[1] = 1'b1; B[1] = 1'b1;
        #80 A[2] = 1'b1; B[2] = 1'b1;
        #160 A[3] = 1'b1; B[3] = 1'b1;

        #320 $finish;
    end


    always #25 clk = ~clk;
    initial begin
        $monitor("Time: %0t | A = %b | B = %b | sum = %b (s0=%b, s1=%b, s2=%b, s3=%b) | c4 (c4) = %b",
                 $time, A, B, sum, sum[0], sum[1], sum[2], sum[3], c4);
    end
endmodule

VERILOG/test.vcd
$date
	Wed Nov 20 12:04:53 2024
$end
$version
	Icarus Verilog
$end
$timescale
	1ps
$end
$scope module testbench $end
$var wire 4 ! sum [3:0] $end
$var wire 1 " c4 $end
$var reg 4 # A [3:0] $end
$var reg 4 $ B [3:0] $end
$var reg 1 % clk $end
$var reg 1 & reset $end
$scope module uut $end
$var wire 4 ' A [3:0] $end
$var wire 4 ( B [3:0] $end
$var wire 1 ) C0 $end
$var wire 1 % clk $end
$var wire 1 & reset $end
$var wire 4 * sum_int [3:0] $end
$var wire 4 + sum [3:0] $end
$var wire 1 , c4_int $end
$var wire 1 " c4 $end
$var wire 4 - B_ff [3:0] $end
$var wire 4 . A_ff [3:0] $end
$scope module cla_inst $end
$var wire 4 / A [3:0] $end
$var wire 4 0 B [3:0] $end
$var wire 1 ) C0 $end
$var wire 1 1 C1 $end
$var wire 1 2 C2 $end
$var wire 1 3 C3 $end
$var wire 1 4 C4 $end
$var wire 1 5 G0 $end
$var wire 1 6 G1 $end
$var wire 1 7 G2 $end
$var wire 1 8 G3 $end
$var wire 1 9 P0 $end
$var wire 1 : P1 $end
$var wire 1 ; P2 $end
$var wire 1 < P3 $end
$var wire 1 , c4 $end
$var wire 4 = sum [3:0] $end
$upscope $end
$scope module dff_a0 $end
$var wire 1 % clk $end
$var wire 1 > d $end
$var wire 1 & reset $end
$var reg 1 ? q $end
$upscope $end
$scope module dff_a1 $end
$var wire 1 % clk $end
$var wire 1 @ d $end
$var wire 1 & reset $end
$var reg 1 A q $end
$upscope $end
$scope module dff_a2 $end
$var wire 1 % clk $end
$var wire 1 B d $end
$var wire 1 & reset $end
$var reg 1 C q $end
$upscope $end
$scope module dff_a3 $end
$var wire 1 % clk $end
$var wire 1 D d $end
$var wire 1 & reset $end
$var reg 1 E q $end
$upscope $end
$scope module dff_b0 $end
$var wire 1 % clk $end
$var wire 1 F d $end
$var wire 1 & reset $end
$var reg 1 G q $end
$upscope $end
$scope module dff_b1 $end
$var wire 1 % clk $end
$var wire 1 H d $end
$var wire 1 & reset $end
$var reg 1 I q $end
$upscope $end
$scope module dff_b2 $end
$var wire 1 % clk $end
$var wire 1 J d $end
$var wire 1 & reset $end
$var reg 1 K q $end
$upscope $end
$scope module dff_b3 $end
$var wire 1 % clk $end
$var wire 1 L d $end
$var wire 1 & reset $end
$var reg 1 M q $end
$upscope $end
$scope module dff_c4 $end
$var wire 1 % clk $end
$var wire 1 , d $end
$var wire 1 & reset $end
$var reg 1 " q $end
$upscope $end
$scope module dff_s0 $end
$var wire 1 % clk $end
$var wire 1 N d $end
$var wire 1 & reset $end
$var reg 1 O q $end
$upscope $end
$scope module dff_s1 $end
$var wire 1 % clk $end
$var wire 1 P d $end
$var wire 1 & reset $end
$var reg 1 Q q $end
$upscope $end
$scope module dff_s2 $end
$var wire 1 % clk $end
$var wire 1 R d $end
$var wire 1 & reset $end
$var reg 1 S q $end
$upscope $end
$scope module dff_s3 $end
$var wire 1 % clk $end
$var wire 1 T d $end
$var wire 1 & reset $end
$var reg 1 U q $end
$upscope $end
$upscope $end
$upscope $end
$enddefinitions $end
#0
$dumpvars
0U
0T
0S
0R
0Q
0P
0O
0N
0M
0L
0K
0J
0I
0H
0G
0F
0E
0D
0C
0B
0A
0@
0?
0>
b0 =
0<
0;
0:
09
08
07
06
05
04
03
02
01
b0 0
b0 /
b0 .
b0 -
0,
b0 +
b0 *
0)
b0 (
b0 '
1&
0%
b0 $
b0 #
0"
b0 !
$end
#10000
0&
#25000
1%
#30000
1F
1>
b1 $
b1 (
b1 #
b1 '
#50000
0%
#70000
1H
1@
b11 $
b11 (
b11 #
b11 '
#75000
1R
1P
b110 *
b110 =
12
11
15
16
1?
b11 .
b11 /
1A
1G
b11 -
b11 0
1I
1%
#100000
0%
#125000
1S
b110 !
b110 +
1Q
1%
#150000
1J
1B
0%
b111 $
b111 (
b111 #
b111 '
#175000
1T
b1110 *
b1110 =
13
17
b111 .
b111 /
1C
b111 -
b111 0
1K
1%
#200000
0%
#225000
b1110 !
b1110 +
1U
1%
#250000
0%
#275000
1%
#300000
0%
#310000
1L
1D
b1111 $
b1111 (
b1111 #
b1111 '
#325000
1,
14
18
b1111 -
b1111 0
1M
b1111 .
b1111 /
1E
1%
#350000
0%
#375000
1"
1%
